linkable/__init__.py
linkable/emoji.py
linkable/helpers.py
linkable/parser.py
linkable/patterns.py
linkable/tld_list.py
linkable/validators.py
linkable-0.2.2.dist-info/LICENSE
linkable-0.2.2.dist-info/METADATA
linkable-0.2.2.dist-info/WHEEL
linkable-0.2.2.dist-info/top_level.txt
linkable-0.2.2.dist-info/RECORD
