Metadata-Version: 2.1
Name: linkable
Version: 0.2.2
Summary: Detect URL, Email, Hashtag and Mention from plain-text and convert into HTML hyperlink.
Home-page: https://github.com/meyt/linkable-py
Author: Mahdi Ghane.g
Author-email: UNKNOWN
License: MIT License
Platform: UNKNOWN
Classifier: Environment :: Console
Classifier: Environment :: Web Environment
Classifier: Intended Audience :: Developers
Classifier: Natural Language :: English
Classifier: Development Status :: 3 - Alpha
Classifier: License :: OSI Approved :: MIT License
Classifier: Operating System :: OS Independent
Classifier: Programming Language :: Python :: 3.4
Classifier: Programming Language :: Python :: 3.5
Classifier: Programming Language :: Python :: 3.6
Classifier: Topic :: Software Development
Classifier: Topic :: Software Development :: Libraries
Classifier: Topic :: Software Development :: Libraries :: Python Modules
Classifier: Topic :: Text Processing
Classifier: Topic :: Text Processing :: Markup :: HTML
